circular_client/__init__.py
circular_client-0.1.3.dist-info/WHEEL
circular_client-0.1.3.dist-info/METADATA
circular_client-0.1.3.dist-info/RECORD
