Metadata-Version: 2.1
Name: circular-client
Version: 0.1.3
Summary: 
Author: CircularNetwork
Author-email: info@circularnetwork.io
Requires-Python: >=3.6,<4.0
Classifier: Programming Language :: Python :: 3
Classifier: Programming Language :: Python :: 3.6
Classifier: Programming Language :: Python :: 3.7
Classifier: Programming Language :: Python :: 3.8
Classifier: Programming Language :: Python :: 3.9
Requires-Dist: python-dateutil (>=2.8.2,<3.0.0)
Requires-Dist: requests (>=2.23.0,<3.0.0)
